modules/__init__.py
modules/az.py
modules/enums.py
modules/exceptions.py
modules/logging_util.py
modules/main.py
modules/cli/__init__.py
modules/cli/args.py
modules/cli/parser.py
modules/cli/user_config.py
modules/cli/validator.py
modules/entities/__init__.py
modules/entities/apk.py
modules/entities/criteria.py
modules/entities/entity.py
modules/entities/source.py
modules/entities/value.py
modules/entities/dataset/__init__.py
modules/entities/dataset/dataset.py
modules/entities/dataset/filtered_dataset.py
modules/resources/__init__.py
modules/resources/logging.yaml
modules/services/__init__.py
modules/services/apk_evaluator.py
modules/services/dataset_downloader.py
modules/services/metadata_saver.py
modules/services/random_picker.py
modules/services/url_constructor.py
azoo-1.2.2.dist-info/LICENSE
azoo-1.2.2.dist-info/METADATA
azoo-1.2.2.dist-info/WHEEL
azoo-1.2.2.dist-info/entry_points.txt
azoo-1.2.2.dist-info/top_level.txt
azoo-1.2.2.dist-info/RECORD
