Metadata-Version: 2.1
Name: azoo
Version: 1.2.2
Summary: Downloads apks from androzoo repository https://androzoo.uni.lu/
Home-page: https://github.com/ArtemKushnerov/az
Author: Artsiom Kushnariou
Author-email: kushnerovartem@gmail.com
License: UNKNOWN
Platform: UNKNOWN
Classifier: Programming Language :: Python :: 3.6
Classifier: License :: OSI Approved :: MIT License
Classifier: Operating System :: OS Independent
Requires-Dist: click (==6.7)
Requires-Dist: setuptools (==38.5.1)
Requires-Dist: python-dateutil (==2.7.2)
Requires-Dist: PyYAML (==4.2b1)
Requires-Dist: requests (==2.20.0)
